{"_type":"export","__export_format":4,"__export_date":"2022-03-20T17:44:26.239Z","__export_source":"insomnia.desktop.app:v2022.2.0","resources":[{"_id":"req_76460b8f2f564b3b8474578b26bf3d98","parentId":"wrk_2422787f069340669a17ddbcf2090bf9","modified":1647798226896,"created":1647798140481,"url":"https://translate.api.skitzen.com/translate","name":"translation","description":"","method":"POST","body":{"mimeType":"application/json","text":"{\n\t\"q\": \"this sentence should be in polish\",\n\t\"source\": \"en\",\n\t\"target\": \"pl\",\n\t\"format\": \"text\"\n}"},"parameters":[],"headers":[{"name":"Content-Type","value":"application/json"}],"authentication":{},"metaSortKey":-1647798140481,"isPrivate":false,"settingStoreCookies":true,"settingSendCookies":true,"settingDisableRenderRequestBody":false,"settingEncodeUrl":true,"settingRebuildPath":true,"settingFollowRedirects":"global","_type":"request"},{"_id":"wrk_2422787f069340669a17ddbcf2090bf9","parentId":null,"modified":1647798045359,"created":1647798045359,"name":"rest","description":"","scope":"collection","_type":"workspace"},{"_id":"req_dd29da73036d4e00a3a7394d666c2fa0","parentId":"wrk_2422787f069340669a17ddbcf2090bf9","modified":1647798107648,"created":1647798095696,"url":"https://api.genderize.io/?name=Michal","name":"gender","description":"","method":"GET","body":{},"parameters":[],"headers":[],"authentication":{},"metaSortKey":-1647798095696,"isPrivate":false,"settingStoreCookies":true,"settingSendCookies":true,"settingDisableRenderRequestBody":false,"settingEncodeUrl":true,"settingRebuildPath":true,"settingFollowRedirects":"global","_type":"request"},{"_id":"req_c227e0c0a1214afa8bc65eef5a91da7c","parentId":"wrk_2422787f069340669a17ddbcf2090bf9","modified":1647798080675,"created":1647798079287,"url":"https://v2.jokeapi.dev/joke/Pun?type=twopart","name":"joke","description":"","method":"GET","body":{},"parameters":[],"headers":[],"authentication":{},"metaSortKey":-1647798079287,"isPrivate":false,"settingStoreCookies":true,"settingSendCookies":true,"settingDisableRenderRequestBody":false,"settingEncodeUrl":true,"settingRebuildPath":true,"settingFollowRedirects":"global","_type":"request"},{"_id":"env_4a68864830ab41432563d34ad512c17bb262e496","parentId":"wrk_2422787f069340669a17ddbcf2090bf9","modified":1647798045370,"created":1647798045370,"name":"Base Environment","data":{},"dataPropertyOrder":null,"color":null,"isPrivate":false,"metaSortKey":1647798045370,"_type":"environment"},{"_id":"jar_4a68864830ab41432563d34ad512c17bb262e496","parentId":"wrk_2422787f069340669a17ddbcf2090bf9","modified":1647798045373,"created":1647798045373,"name":"Default Jar","cookies":[],"_type":"cookie_jar"},{"_id":"spc_e30abb9f76e745a5b1a702797182edf3","parentId":"wrk_2422787f069340669a17ddbcf2090bf9","modified":1647798045362,"created":1647798045362,"fileName":"rest","contents":"","contentType":"yaml","_type":"api_spec"}]}